{
  "version": 1,
  "serviceConfiguration": {
    "apiName": "coven",
    "serviceName": "AppSync",
    "gqlSchemaPath": "/tmp/amplify-58817e2b-d910-42f8-9ae9-5ba60c33d5ea/amplify/backend/api/coven/schema.graphql",
    "defaultAuthType": {
      "mode": "API_KEY",
      "keyDescription": "api key description",
      "expirationTime": 30
    },
    "conflictResolution": {
      "defaultResolutionStrategy": {
        "type": "AUTOMERGE"
      }
    },
    "additionalAuthTypes": [
      {
        "mode": "AWS_IAM"
      }
    ]
  }
}